avirtech_spraying_jiyi_wp_lib/__init__.py
avirtech_spraying_jiyi_wp_lib/avirtech_spraying_jiyi_wp.py
avirtech_spraying_jiyi_wp_lib-0.0.4.dist-info/METADATA
avirtech_spraying_jiyi_wp_lib-0.0.4.dist-info/WHEEL
avirtech_spraying_jiyi_wp_lib-0.0.4.dist-info/top_level.txt
avirtech_spraying_jiyi_wp_lib-0.0.4.dist-info/RECORD
