Metadata-Version: 2.1
Name: avirtech-spraying-jiyi-wp-lib
Version: 0.0.4
Summary: Avirtech Python Library to Generate JIYI Drone Spraying Track Using Waypoint Data From Avirplaner
Home-page: 
Author: Mohammad ILham R
Author-email: ilhamr.mohammad@gmail.com
License: MIT
Platform: UNKNOWN
Classifier: Intended Audience :: Developers
Classifier: License :: OSI Approved :: MIT License
Classifier: Programming Language :: Python
Classifier: Programming Language :: Python :: 3
Classifier: Programming Language :: Python :: 3.6
Classifier: Programming Language :: Python :: 3.7
Classifier: Programming Language :: Python :: 3.8
Classifier: Programming Language :: Python :: 3.9
Classifier: Operating System :: OS Independent
Requires-Dist: simpledbf
Requires-Dist: numpy
Requires-Dist: matplotlib
Requires-Dist: pathlib
